[
  {
    "inputs": [
      {
        "internalType": "contract IProjects",
        "name": "_projects",
        "type": "address"
      },
      {
        "internalType": "contract IOperatorStore",
        "name": "_operatorStore",
        "type": "address"
      },
      {
        "internalType": "contract ITerminalDirectory",
        "name": "_terminalDirectory",
        "type": "address"
      }
    ],
    "stateMutability": "nonpayable",
    "type": "constructor"
  },
  {
    "anonymous": false,
    "inputs": [
      {
        "indexed": true,
        "internalType": "uint256",
        "name": "projectId",
        "type": "uint256"
      },
      {
        "indexed": false,
        "internalType": "string",
        "name": "name",
        "type": "string"
      },
      {
        "indexed": false,
        "internalType": "string",
        "name": "symbol",
        "type": "string"
      },
      {
        "indexed": false,
        "internalType": "address",
        "name": "caller",
        "type": "address"
      }
    ],
    "name": "Issue",
    "type": "event"
  },
  {
    "anonymous": false,
    "inputs": [
      {
        "indexed": true,
        "internalType": "address",
        "name": "holder",
        "type": "address"
      },
      {
        "indexed": true,
        "internalType": "uint256",
        "name": "projectId",
        "type": "uint256"
      },
      {
        "indexed": false,
        "internalType": "uint256",
        "name": "amount",
        "type": "uint256"
      },
      {
        "indexed": false,
        "internalType": "address",
        "name": "caller",
        "type": "address"
      }
    ],
    "name": "Lock",
    "type": "event"
  },
  {
    "anonymous": false,
    "inputs": [
      {
        "indexed": true,
        "internalType": "address",
        "name": "holder",
        "type": "address"
      },
      {
        "indexed": true,
        "internalType": "uint256",
        "name": "projectId",
        "type": "uint256"
      },
      {
        "indexed": false,
        "internalType": "uint256",
        "name": "amount",
        "type": "uint256"
      },
      {
        "indexed": false,
        "internalType": "bool",
        "name": "convertedTickets",
        "type": "bool"
      },
      {
        "indexed": false,
        "internalType": "bool",
        "name": "preferUnstakedTickets",
        "type": "bool"
      },
      {
        "indexed": false,
        "internalType": "address",
        "name": "controller",
        "type": "address"
      }
    ],
    "name": "Print",
    "type": "event"
  },
  {
    "anonymous": false,
    "inputs": [
      {
        "indexed": true,
        "internalType": "address",
        "name": "holder",
        "type": "address"
      },
      {
        "indexed": true,
        "internalType": "uint256",
        "name": "projectId",
        "type": "uint256"
      },
      {
        "indexed": false,
        "internalType": "uint256",
        "name": "amount",
        "type": "uint256"
      },
      {
        "indexed": false,
        "internalType": "uint256",
        "name": "stakedTickets",
        "type": "uint256"
      },
      {
        "indexed": false,
        "internalType": "bool",
        "name": "preferUnstaked",
        "type": "bool"
      },
      {
        "indexed": false,
        "internalType": "address",
        "name": "controller",
        "type": "address"
      }
    ],
    "name": "Redeem",
    "type": "event"
  },
  {
    "anonymous": false,
    "inputs": [
      {
        "indexed": true,
        "internalType": "address",
        "name": "holder",
        "type": "address"
      },
      {
        "indexed": true,
        "internalType": "uint256",
        "name": "projectId",
        "type": "uint256"
      },
      {
        "indexed": false,
        "internalType": "uint256",
        "name": "amount",
        "type": "uint256"
      },
      {
        "indexed": false,
        "internalType": "address",
        "name": "caller",
        "type": "address"
      }
    ],
    "name": "Stake",
    "type": "event"
  },
  {
    "anonymous": false,
    "inputs": [
      {
        "indexed": true,
        "internalType": "address",
        "name": "holder",
        "type": "address"
      },
      {
        "indexed": true,
        "internalType": "uint256",
        "name": "projectId",
        "type": "uint256"
      },
      {
        "indexed": true,
        "internalType": "address",
        "name": "recipient",
        "type": "address"
      },
      {
        "indexed": false,
        "internalType": "uint256",
        "name": "amount",
        "type": "uint256"
      },
      {
        "indexed": false,
        "internalType": "address",
        "name": "caller",
        "type": "address"
      }
    ],
    "name": "Transfer",
    "type": "event"
  },
  {
    "anonymous": false,
    "inputs": [
      {
        "indexed": true,
        "internalType": "address",
        "name": "holder",
        "type": "address"
      },
      {
        "indexed": true,
        "internalType": "uint256",
        "name": "projectId",
        "type": "uint256"
      },
      {
        "indexed": false,
        "internalType": "uint256",
        "name": "amount",
        "type": "uint256"
      },
      {
        "indexed": false,
        "internalType": "address",
        "name": "caller",
        "type": "address"
      }
    ],
    "name": "Unlock",
    "type": "event"
  },
  {
    "anonymous": false,
    "inputs": [
      {
        "indexed": true,
        "internalType": "address",
        "name": "holder",
        "type": "address"
      },
      {
        "indexed": true,
        "internalType": "uint256",
        "name": "projectId",
        "type": "uint256"
      },
      {
        "indexed": false,
        "internalType": "uint256",
        "name": "amount",
        "type": "uint256"
      },
      {
        "indexed": false,
        "internalType": "address",
        "name": "caller",
        "type": "address"
      }
    ],
    "name": "Unstake",
    "type": "event"
  },
  {
    "inputs": [
      {
        "internalType": "address",
        "name": "_holder",
        "type": "address"
      },
      {
        "internalType": "uint256",
        "name": "_projectId",
        "type": "uint256"
      }
    ],
    "name": "balanceOf",
    "outputs": [
      {
        "internalType": "uint256",
        "name": "balance",
        "type": "uint256"
      }
    ],
    "stateMutability": "view",
    "type": "function"
  },
  {
    "inputs": [
      {
        "internalType": "uint256",
        "name": "_projectId",
        "type": "uint256"
      },
      {
        "internalType": "string",
        "name": "_name",
        "type": "string"
      },
      {
        "internalType": "string",
        "name": "_symbol",
        "type": "string"
      }
    ],
    "name": "issue",
    "outputs": [],
    "stateMutability": "nonpayable",
    "type": "function"
  },
  {
    "inputs": [
      {
        "internalType": "address",
        "name": "_holder",
        "type": "address"
      },
      {
        "internalType": "uint256",
        "name": "_projectId",
        "type": "uint256"
      },
      {
        "internalType": "uint256",
        "name": "_amount",
        "type": "uint256"
      }
    ],
    "name": "lock",
    "outputs": [],
    "stateMutability": "nonpayable",
    "type": "function"
  },
  {
    "inputs": [
      {
        "internalType": "address",
        "name": "",
        "type": "address"
      },
      {
        "internalType": "address",
        "name": "",
        "type": "address"
      },
      {
        "internalType": "uint256",
        "name": "",
        "type": "uint256"
      }
    ],
    "name": "lockedBalanceBy",
    "outputs": [
      {
        "internalType": "uint256",
        "name": "",
        "type": "uint256"
      }
    ],
    "stateMutability": "view",
    "type": "function"
  },
  {
    "inputs": [
      {
        "internalType": "address",
        "name": "",
        "type": "address"
      },
      {
        "internalType": "uint256",
        "name": "",
        "type": "uint256"
      }
    ],
    "name": "lockedBalanceOf",
    "outputs": [
      {
        "internalType": "uint256",
        "name": "",
        "type": "uint256"
      }
    ],
    "stateMutability": "view",
    "type": "function"
  },
  {
    "inputs": [],
    "name": "operatorStore",
    "outputs": [
      {
        "internalType": "contract IOperatorStore",
        "name": "",
        "type": "address"
      }
    ],
    "stateMutability": "view",
    "type": "function"
  },
  {
    "inputs": [
      {
        "internalType": "address",
        "name": "_holder",
        "type": "address"
      },
      {
        "internalType": "uint256",
        "name": "_projectId",
        "type": "uint256"
      },
      {
        "internalType": "uint256",
        "name": "_amount",
        "type": "uint256"
      },
      {
        "internalType": "bool",
        "name": "_preferUnstakedTickets",
        "type": "bool"
      }
    ],
    "name": "print",
    "outputs": [],
    "stateMutability": "nonpayable",
    "type": "function"
  },
  {
    "inputs": [],
    "name": "projects",
    "outputs": [
      {
        "internalType": "contract IProjects",
        "name": "",
        "type": "address"
      }
    ],
    "stateMutability": "view",
    "type": "function"
  },
  {
    "inputs": [
      {
        "internalType": "address",
        "name": "_holder",
        "type": "address"
      },
      {
        "internalType": "uint256",
        "name": "_projectId",
        "type": "uint256"
      },
      {
        "internalType": "uint256",
        "name": "_amount",
        "type": "uint256"
      },
      {
        "internalType": "bool",
        "name": "_preferUnstaked",
        "type": "bool"
      }
    ],
    "name": "redeem",
    "outputs": [],
    "stateMutability": "nonpayable",
    "type": "function"
  },
  {
    "inputs": [
      {
        "internalType": "address",
        "name": "_holder",
        "type": "address"
      },
      {
        "internalType": "uint256",
        "name": "_projectId",
        "type": "uint256"
      },
      {
        "internalType": "uint256",
        "name": "_amount",
        "type": "uint256"
      }
    ],
    "name": "stake",
    "outputs": [],
    "stateMutability": "nonpayable",
    "type": "function"
  },
  {
    "inputs": [
      {
        "internalType": "address",
        "name": "",
        "type": "address"
      },
      {
        "internalType": "uint256",
        "name": "",
        "type": "uint256"
      }
    ],
    "name": "stakedBalanceOf",
    "outputs": [
      {
        "internalType": "uint256",
        "name": "",
        "type": "uint256"
      }
    ],
    "stateMutability": "view",
    "type": "function"
  },
  {
    "inputs": [
      {
        "internalType": "uint256",
        "name": "",
        "type": "uint256"
      }
    ],
    "name": "stakedTotalSupplyOf",
    "outputs": [
      {
        "internalType": "uint256",
        "name": "",
        "type": "uint256"
      }
    ],
    "stateMutability": "view",
    "type": "function"
  },
  {
    "inputs": [],
    "name": "terminalDirectory",
    "outputs": [
      {
        "internalType": "contract ITerminalDirectory",
        "name": "",
        "type": "address"
      }
    ],
    "stateMutability": "view",
    "type": "function"
  },
  {
    "inputs": [
      {
        "internalType": "uint256",
        "name": "",
        "type": "uint256"
      }
    ],
    "name": "ticketsOf",
    "outputs": [
      {
        "internalType": "contract ITickets",
        "name": "",
        "type": "address"
      }
    ],
    "stateMutability": "view",
    "type": "function"
  },
  {
    "inputs": [
      {
        "internalType": "uint256",
        "name": "_projectId",
        "type": "uint256"
      }
    ],
    "name": "totalSupplyOf",
    "outputs": [
      {
        "internalType": "uint256",
        "name": "supply",
        "type": "uint256"
      }
    ],
    "stateMutability": "view",
    "type": "function"
  },
  {
    "inputs": [
      {
        "internalType": "address",
        "name": "_holder",
        "type": "address"
      },
      {
        "internalType": "uint256",
        "name": "_projectId",
        "type": "uint256"
      },
      {
        "internalType": "uint256",
        "name": "_amount",
        "type": "uint256"
      },
      {
        "internalType": "address",
        "name": "_recipient",
        "type": "address"
      }
    ],
    "name": "transfer",
    "outputs": [],
    "stateMutability": "nonpayable",
    "type": "function"
  },
  {
    "inputs": [
      {
        "internalType": "address",
        "name": "_holder",
        "type": "address"
      },
      {
        "internalType": "uint256",
        "name": "_projectId",
        "type": "uint256"
      },
      {
        "internalType": "uint256",
        "name": "_amount",
        "type": "uint256"
      }
    ],
    "name": "unlock",
    "outputs": [],
    "stateMutability": "nonpayable",
    "type": "function"
  },
  {
    "inputs": [
      {
        "internalType": "address",
        "name": "_holder",
        "type": "address"
      },
      {
        "internalType": "uint256",
        "name": "_projectId",
        "type": "uint256"
      },
      {
        "internalType": "uint256",
        "name": "_amount",
        "type": "uint256"
      }
    ],
    "name": "unstake",
    "outputs": [],
    "stateMutability": "nonpayable",
    "type": "function"
  }
]